odoo8_addon_partner_phone_extension-8.0.1.0.0.99.dev7-py2.7-nspkg.pth
odoo8_addon_partner_phone_extension-8.0.1.0.0.99.dev7.dist-info/METADATA
odoo8_addon_partner_phone_extension-8.0.1.0.0.99.dev7.dist-info/RECORD
odoo8_addon_partner_phone_extension-8.0.1.0.0.99.dev7.dist-info/WHEEL
odoo8_addon_partner_phone_extension-8.0.1.0.0.99.dev7.dist-info/namespace_packages.txt
odoo8_addon_partner_phone_extension-8.0.1.0.0.99.dev7.dist-info/top_level.txt
odoo_addons/partner_phone_extension/README.rst
odoo_addons/partner_phone_extension/__init__.py
odoo_addons/partner_phone_extension/__openerp__.py
odoo_addons/partner_phone_extension/i18n/fr.po
odoo_addons/partner_phone_extension/i18n/partner_phone_extension.pot
odoo_addons/partner_phone_extension/i18n/sl.po
odoo_addons/partner_phone_extension/models/__init__.py
odoo_addons/partner_phone_extension/models/res_partner.py
odoo_addons/partner_phone_extension/static/description/icon.png
odoo_addons/partner_phone_extension/views/res_partner_view.xml
