Metadata-Version: 2.1
Name: odoo8-addon-partner-phone-extension
Version: 8.0.1.0.0.99.dev7
Summary: Partner Phone Number Extension
Home-page: http://www.savoirfairelinux.com
Author: Savoir-faire Linux, Eficent, SerpentCS, Odoo Community Association (OCA)
Author-email: support@odoo-community.org
License: AGPL-3
Platform: UNKNOWN
Classifier: Programming Language :: Python
Classifier: Framework :: Odoo
Classifier: License :: OSI Approved :: GNU Affero General Public License v3
Requires-Python: ~=2.7
Requires-Dist: odoo (<9.0a,>=8.0a)
